zenka/__init__.py
zenka/src/assets/font/impact.ttf
zenka/src/generator/style_one.py
zenka/src/generator/style_one_profile.py
zenka/src/generator/style_two.py
zenka/src/model/api.py
zenka/src/model/assets.py
zenka/src/model/base.py
zenka/src/model/generator.py
zenka/src/tools/__init__.py
zenka/src/tools/api.py
zenka/src/tools/cache.py
zenka/src/tools/error.py
zenka/src/tools/git.py
zenka/src/tools/http.py
zenka/src/tools/options.py
zenka/src/tools/pill/__init__.py
zenka/src/tools/pill/color.py
zenka/src/tools/pill/color_control.py
zenka/src/tools/pill/image_control.py
zenka/src/tools/pill/text_control.py
zenka/zenka.py
zenka-0.2.7.dist-info/LICENSE
zenka-0.2.7.dist-info/METADATA
zenka-0.2.7.dist-info/WHEEL
zenka-0.2.7.dist-info/RECORD
