Metadata-Version: 2.3
Name: zenka
Version: 0.2.7
Summary: Python module for processing EnkaNetwork API and creating profile cards, character
License: MIT License with Additional Restrictions
Keywords: enka,enkanetwork,zenka,zerozonezenless,zenless,zero,zone,zzz,api,card
Author: DEViantUA
Author-email: deviantapi@gmail.com
Requires-Python: >=3.9,<4.0
Classifier: License :: Other/Proprietary License
Classifier: Programming Language :: Python :: 3
Classifier: Programming Language :: Python :: 3.9
Classifier: Programming Language :: Python :: 3.10
Classifier: Programming Language :: Python :: 3.11
Classifier: Programming Language :: Python :: 3.12
Classifier: Programming Language :: Python :: 3.13
Requires-Dist: Pillow
Requires-Dist: aiofiles
Requires-Dist: aiohttp
Requires-Dist: beautifulsoup4
Requires-Dist: cachetools
Requires-Dist: more-itertools
Requires-Dist: numpy
Requires-Dist: pydantic
Project-URL: Homepage, https://github.com/DEViantUA/Zenka
Project-URL: Repository, https://github.com/DEViantUA/Zenka
